bosons/__init__.py
bosons/show.py
bosons-0.0.1.dist-info/METADATA
bosons-0.0.1.dist-info/WHEEL
bosons-0.0.1.dist-info/top_level.txt
bosons-0.0.1.dist-info/RECORD
