Metadata-Version: 2.1
Name: bosons
Version: 0.0.1
Summary: A basic hello package
Home-page: UNKNOWN
Author: Glauco
Author-email: <glauco.endrigo@hotmail.com>
License: UNKNOWN
Keywords: python
Platform: UNKNOWN
Classifier: Development Status :: 1 - Planning
Classifier: Intended Audience :: Developers
Classifier: Programming Language :: Python :: 3.8
Classifier: Operating System :: Unix
Classifier: Operating System :: POSIX :: Linux
Classifier: Operating System :: Microsoft :: Windows
